uart_wifi/__init__.py
uart_wifi/__main__.py
uart_wifi/communication.py
uart_wifi/errors.py
uart_wifi/response.py
uart_wifi/simulate_printer.py
uart_wifi/scripts/__init__.py
uart_wifi/scripts/fake_printer.py
uart_wifi/scripts/monox.py
uart_wifi-0.2.1.data/scripts/fake_printer
uart_wifi-0.2.1.data/scripts/fake_printer.py
uart_wifi-0.2.1.data/scripts/monox
uart_wifi-0.2.1.data/scripts/monox.py
uart_wifi-0.2.1.dist-info/LICENSE
uart_wifi-0.2.1.dist-info/METADATA
uart_wifi-0.2.1.dist-info/WHEEL
uart_wifi-0.2.1.dist-info/top_level.txt
uart_wifi-0.2.1.dist-info/RECORD
