Metadata-Version: 2.1
Name: uart-wifi
Version: 0.2.1
Summary: Interface for Anycubic Mono X and similar printers.
Home-page: https://github.com/adamoutler/anycubic-python
Author: Adam Outler
Author-email: adamoutler@hackedyour.info
Project-URL: Bug Tracker, https://github.com/adamoutler/anycubic-python/issues
Classifier: Programming Language :: Python :: 3
Classifier: License :: OSI Approved :: GNU General Public License v3 (GPLv3)
Classifier: Operating System :: OS Independent
Classifier: Development Status :: 2 - Pre-Alpha
Classifier: Intended Audience :: Developers
Classifier: Natural Language :: English
Classifier: Topic :: Communications
Classifier: Topic :: Home Automation
Classifier: Topic :: Printing
Requires-Python: >=3.6
License-File: LICENSE
